tabheatcal/__init__.py
tabheatcal/assets.py
tabheatcal/tabheatcal.py
tabheatcal/tabheatcal_demo.html
tabheatcal/template.html
tabheatcal-0.0.2.dist-info/METADATA
tabheatcal-0.0.2.dist-info/WHEEL
tabheatcal-0.0.2.dist-info/RECORD
