Metadata-Version: 2.4
Name: tabheatcal
Version: 0.0.2
Summary: tabheatcal - Heatmap visualization with easy value inspection
Project-URL: Homepage, https://github.com/ts-kontakt/tabheatcal
Project-URL: Issues, https://github.com/ts-kontakt/tabheatcal/issues
Author-email: Tomasz Sługocki <ts.kontakt@gmail.com>
License-Expression: MIT
Requires-Dist: jinja2
Requires-Dist: numpy
